mds_exporter/__init__.py
mds_exporter/main.py
mds_exporter/token_storage.py
mds_exporter-0.1.0.dist-info/METADATA
mds_exporter-0.1.0.dist-info/WHEEL
mds_exporter-0.1.0.dist-info/entry_points.txt
mds_exporter-0.1.0.dist-info/licenses/LICENSE
mds_exporter-0.1.0.dist-info/RECORD
