Metadata-Version: 2.4
Name: mds-exporter
Version: 0.1.0
Summary: A CLI tool for bulk downloading from museum data service API with rich progress tracking.
Project-URL: Homepage, https://github.com/wrmthorne/mds-exporter
Project-URL: Bug Reports, https://github.com/wrmthorne/mds-exporter/issues
Project-URL: Source, https://github.com/wrmthorne/mds-exporter
Author-email: William Thorne <wthorne1@sheffield.ac.uk>
License: MIT
License-File: LICENSE
Keywords: api,bulk-download,cli,data,museum
Classifier: Development Status :: 3 - Alpha
Classifier: Intended Audience :: Developers
Classifier: Intended Audience :: Education
Classifier: License :: OSI Approved :: MIT License
Classifier: Operating System :: OS Independent
Classifier: Programming Language :: Python :: 3
Classifier: Programming Language :: Python :: 3.12
Classifier: Topic :: Internet :: WWW/HTTP :: Dynamic Content
Classifier: Topic :: Software Development :: Libraries :: Python Modules
Classifier: Topic :: Utilities
Requires-Python: >=3.12
Requires-Dist: click>=8.2.1
Requires-Dist: httpx>=0.28.1
Requires-Dist: requests>=2.32.4
Requires-Dist: rich>=14.1.0
Requires-Dist: zstandard>=0.23.0
